Workbook

Sheet Instructions
A1: MS Excel Practical Exam
A2: Total Questions: 30
A3: Difficulty Level: Medium
A4: Syllabus: Formulas, Logical Functions, Lookups, INDEX-MATCH, Pivot Tables & Charts, Data Analysis
A5: Attempt all questions using appropriate Excel tools/functions.

Sheet Sales_Data
A1: Order_ID | B1: Region | C1: Salesperson | D1: Product | E1: Quantity | F1: Unit_Price | G1: Sales_Date | H1: Total_Sales | I1: GST_% | J1: GST_Amount | K1: Final_Amount | L1: Quantity_Class | M1: Month_Name | N1: Product_Category | O1: Salesperson_Initials | P1: Rounded_Unit_Price | R1: Sales Analysis | S1: Result / Formula
A2: 301 | B2: North | C2: Amit | D2: Laptop | E2: 2 | F2: 45000 | G2: 45662 | H2: =E2*F2 -> 90000 | I2: =VLOOKUP(Sales_Data!D2,Product_Master!$A$2:$C$4,3,FALSE) -> 18 | J2: =H2*I2/100 -> 16200 | K2: =H2+J2 -> 106200 | L2: =IF(E2>3,"High","Low") -> Low | M2: =TEXT(G2,"mmmm") -> January | N2: =INDEX(Product_Master!$B$2:$B$4,MATCH(D2,Product_Master!$A$2:$A$4,0)) -> Electronics | O2: =LEFT(C2,2) -> Am | P2: =ROUND(F2,-3) -> 45000 | R2: Grand Total Final Amount | S2: =SUM(K2:K7) -> 477180
A3: 302 | B3: South | C3: Riya | D3: Mobile | E3: 5 | F3: 15000 | G3: 45664 | H3: =E3*F3 -> 75000 | I3: =VLOOKUP(D3,Product_Master!$A$2:$C$4,3,FALSE) -> 12 | J3: =H3*I3/100 -> 9000 | K3: =H3+J3 -> 84000 | L3: =IF(E3>3,"High","Low") -> High | M3: =TEXT(G3,"mmmm") -> January | N3: =INDEX(Product_Master!$B$2:$B$4,MATCH(D3,Product_Master!$A$2:$A$4,0)) -> Electronics | O3: =LEFT(C3,2) -> Ri | P3: =ROUND(F3,-3) -> 15000 | R3: Total Orders | S3: =COUNTA(A2:A7) -> 6
A4: 303 | B4: East | C4: Kunal | D4: Tablet | E4: 3 | F4: 18000 | G4: 45667 | H4: =E4*F4 -> 54000 | I4: =VLOOKUP(D4,Product_Master!$A$2:$C$4,3,FALSE) -> 12 | J4: =H4*I4/100 -> 6480 | K4: =H4+J4 -> 60480 | L4: =IF(E4>3,"High","Low") -> Low | M4: =TEXT(G4,"mmmm") -> January | N4: =INDEX(Product_Master!$B$2:$B$4,MATCH(D4,Product_Master!$A$2:$A$4,0)) -> Electronics | O4: =LEFT(C4,2) -> Ku | P4: =ROUND(F4,-3) -> 18000 | R4: Maximum Final Amount | S4: =MAX(K2:K7) -> 106200
A5: 304 | B5: West | C5: Neha | D5: Laptop | E5: 1 | F5: 45000 | G5: 45669 | H5: =E5*F5 -> 45000 | I5: =VLOOKUP(D5,Product_Master!$A$2:$C$4,3,FALSE) -> 18 | J5: =H5*I5/100 -> 8100 | K5: =H5+J5 -> 53100 | L5: =IF(E5>3,"High","Low") -> Low | M5: =TEXT(G5,"mmmm") -> January | N5: =INDEX(Product_Master!$B$2:$B$4,MATCH(D5,Product_Master!$A$2:$A$4,0)) -> Electronics | O5: =LEFT(C5,2) -> Ne | P5: =ROUND(F5,-3) -> 45000 | R5: Minimum Final Amount | S5: =MIN(K2:K7) -> 53100
A6: 305 | B6: North | C6: Amit | D6: Mobile | E6: 4 | F6: 15000 | G6: 45672 | H6: =E6*F6 -> 60000 | I6: =VLOOKUP(D6,Product_Master!$A$2:$C$4,3,FALSE) -> 12 | J6: =H6*I6/100 -> 7200 | K6: =H6+J6 -> 67200 | L6: =IF(E6>3,"High","Low") -> High | M6: =TEXT(G6,"mmmm") -> January | N6: =INDEX(Product_Master!$B$2:$B$4,MATCH(D6,Product_Master!$A$2:$A$4,0)) -> Electronics | O6: =LEFT(C6,2) -> Am | P6: =ROUND(F6,-3) -> 15000 | R6: North Total Sales | S6: =SUMIF(B2:B7,"North",H2:H7) -> 150000
A7: 306 | B7: South | C7: Riya | D7: Laptop | E7: 2 | F7: 45000 | G7: 45675 | H7: =E7*F7 -> 90000 | I7: =VLOOKUP(D7,Product_Master!$A$2:$C$4,3,FALSE) -> 18 | J7: =H7*I7/100 -> 16200 | K7: =H7+J7 -> 106200 | L7: =IF(E7>3,"High","Low") -> Low | M7: =TEXT(G7,"mmmm") -> January | N7: =INDEX(Product_Master!$B$2:$B$4,MATCH(D7,Product_Master!$A$2:$A$4,0)) -> Electronics | O7: =LEFT(C7,2) -> Ri | P7: =ROUND(F7,-3) -> 45000 | R7: South Total Sales | S7: =SUMIF(B2:B7,"South",H2:H7) -> 165000
R8: East Total Sales | S8: =SUMIF(B2:B7,"East",H2:H7) -> 54000
R9: West Total Sales | S9: =SUMIF(B2:B7,"West",H2:H7) -> 45000
R10: Laptop Orders in North | S10: =COUNTIFS(D2:D7,"Laptop",B2:B7,"North") -> 1
R11: Duplicate Records | S11: No duplicate records found
R12: Laptop & Qty > 1 | S12: Order IDs 301 and 306
R13: Sorted Order IDs (Descending Final Amount) | S13: 301, 306, 302, 305, 303, 304

Sheet Product_Master
A1: Product | B1: Category | C1: GST_%
A2: Laptop | B2: Electronics | C2: 18
A3: Mobile | B3: Electronics | C3: 12
A4: Tablet | B4: Electronics | C4: 12

Sheet Student_Marks
A1: Student_ID | B1: Name | C1: Maths | D1: Statistics | E1: Excel | F1: Attendance_% | G1: Average_Marks | H1: Eligibility | I1: Student_ID_Name | K1: Student Analysis | L1: Result / Formula
A2: 1 | B2: Rahul | C2: 78 | D2: 82 | E2: 85 | F2: 92 | G2: =AVERAGE(C2:E2) -> 81.666667 | H2: =IF(F2>=85,"Eligible","Not Eligible") -> Eligible | I2: =_xlfn.CONCAT(A2," - ",B2) -> 1 - Rahul | K2: Topper | L2: =INDEX(B2:B6,MATCH(MAX(G2:G6),G2:G6,0)) -> Pooja
A3: 2 | B3: Sneha | C3: 88 | D3: 91 | E3: 90 | F3: 96 | G3: =AVERAGE(C3:E3) -> 89.666667 | H3: =IF(F3>=85,"Eligible","Not Eligible") -> Eligible | I3: =_xlfn.CONCAT(A3," - ",B3) -> 2 - Sneha | K3: Students Attendance > 90% | L3: =COUNTIF(F2:F6,">90") -> 3
A4: 3 | B4: Arjun | C4: 65 | D4: 70 | E4: 72 | F4: 85 | G4: =AVERAGE(C4:E4) -> 69 | H4: =IF(F4>=85,"Eligible","Not Eligible") -> Eligible | I4: =_xlfn.CONCAT(A4," - ",B4) -> 3 - Arjun | K4: Median Statistics Marks | L4: =MEDIAN(D2:D6) -> 82
A5: 4 | B5: Pooja | C5: 92 | D5: 89 | E5: 94 | F5: 98 | G5: =AVERAGE(C5:E5) -> 91.666667 | H5: =IF(F5>=85,"Eligible","Not Eligible") -> Eligible | I5: =_xlfn.CONCAT(A5," - ",B5) -> 4 - Pooja | K5: Standard Deviation of Excel Marks | L5: =_xlfn.STDEV.S(E2:E6) -> 14.737707
A6: 5 | B6: Vikas | C6: 55 | D6: 60 | E6: 58 | F6: 80 | G6: =AVERAGE(C6:E6) -> 57.666667 | H6: =IF(F6>=85,"Eligible","Not Eligible") -> Not Eligible | I6: =_xlfn.CONCAT(A6," - ",B6) -> 5 - Vikas | K6: Protection Status | L6: Sheet prepared for protection in Excel

Sheet Questions
A1: 1. Calculate Total Sales for each order (Quantity × Unit_Price). | B1: Formula / Method | H1: 2
A2: 2. Calculate GST Amount using VLOOKUP from Product_Master. | B2: {=Quantity*Unit_Price} -> #NAME? | H2: 2
A3: 3. Find Final Amount payable (Total Sales + GST). | B3: =VLOOKUP(Product,Product_Master,3,FALSE) | H3: 2
A4: 4. Find Grand Total of Final Amount. | B4: =Total Sales+GST Amount | H4: 2
A5: 5. Count total number of orders using COUNTA. | B5: =SUM(Final Amount) | H5: 2
A6: 6. Find Region-wise total sales using SUMIF. | B6: =COUNTA(Order_ID) | H6: 2
A7: 7. Use IF to classify Quantity as High (>3) or Low (<=3). | B7: =SUMIF(Region,criteria,Total Sales) | H7: 2
A8: 8. Find the maximum and minimum Final Amount. | B8: =IF(Quantity>3,"High","Low") | H8: 2
A9: 9. Extract month name from Sales_Date. | B9: =MAX / MIN(Final Amount) | H9: 2
A10: 10. Sort Sales_Data by Final Amount (Descending). | B10: =TEXT(Sales_Date,"mmmm") | H10: 2
A11: 11. Use INDEX-MATCH to fetch Product Category. | B11: Descending sequence documented | H11: 2
A12: 12. Calculate average marks of each student. | B12: =INDEX(Category,MATCH(Product,...)) | H12: 2
A13: 13. Find the topper based on average marks. | B13: =AVERAGE(Maths:Excel) | H13: 2
A14: 14. Count students with Attendance above 90%. | B14: =INDEX(Name,MATCH(MAX(Average),Average,0)) | H14: 2
... A30: 30. Protect the Student_Marks sheet. | B30: Top row frozen | H30: 2
B31: Use Review > Protect Sheet (no password)
H32: =SUM(H1:H30) -> 60
